{"cameraMode":{"drawMode":0,"name":"Shaded","section":"Shading Mode"},"sceneLighting":true,"audioPlay":false,"sceneViewState":{"showFog":true,"showMaterialUpdate":false,"showSkybox":true,"showFlares":true,"showImageEffects":true,"showParticleSystems":true,"showVisualEffectGraphs":true,"m_FxEnabled":true},"in2DMode":false,"pivot":{"x":-23.659576416015626,"y":17.98218536376953,"z":192.14796447753907},"rotation":{"x":-0.05532834306359291,"y":0.5186941027641296,"z":-0.033663246780633929,"w":-0.852507472038269},"size":233.4460906982422,"orthographic":false}